inspectomat/__init__.py
inspectomat/_version.py
inspectomat/batch_compare_folders.py
inspectomat/clean_empty_dirs.py
inspectomat/cli.py
inspectomat/compare_equal_folders.py
inspectomat/compare_folders.py
inspectomat/config.py
inspectomat/dependency_manager.py
inspectomat/find_big_files.py
inspectomat/find_similar_projects.py
inspectomat/git_projects_audit.py
inspectomat/logger.py
inspectomat/media_deduplicate.py
inspectomat/menu.py
inspectomat/move_batch_duplicates.py
inspectomat/move_duplicate_folders.py
inspectomat/move_nonidentical_files.py
inspectomat/resolve_folder_differences.py
inspectomat-0.1.6.dist-info/licenses/LICENSE
tests/__init__.py
tests/test_clean_empty_dirs.py
tests/test_cli.py
tests/test_config_logger.py
inspectomat-0.1.6.dist-info/METADATA
inspectomat-0.1.6.dist-info/WHEEL
inspectomat-0.1.6.dist-info/entry_points.txt
inspectomat-0.1.6.dist-info/top_level.txt
inspectomat-0.1.6.dist-info/RECORD
