Metadata-Version: 2.4
Name: inspectomat
Version: 0.1.6
Summary: System cleanup and file management toolbox
Author: multigit-com
Author-email: multigit-com <info@multigit.com>
License: MIT
Classifier: Development Status :: 3 - Alpha
Classifier: Intended Audience :: System Administrators
Classifier: Intended Audience :: End Users/Desktop
Classifier: Topic :: System :: Systems Administration
Classifier: Topic :: Utilities
Classifier: Programming Language :: Python :: 3
Classifier: Programming Language :: Python :: 3.6
Classifier: Programming Language :: Python :: 3.7
Classifier: Programming Language :: Python :: 3.8
Classifier: Programming Language :: Python :: 3.9
Classifier: Programming Language :: Python :: 3.10
Classifier: License :: OSI Approved :: Apache Software License
Classifier: Operating System :: OS Independent
Requires-Python: >=3.6
License-File: LICENSE
Provides-Extra: full
Requires-Dist: pillow; extra == "full"
Requires-Dist: numpy; extra == "full"
Requires-Dist: tqdm; extra == "full"
Requires-Dist: psutil; extra == "full"
Dynamic: author
Dynamic: license-file
Dynamic: requires-python
